{
"autoplayBgm":false,"autoplayBgs":false,"battleback1Name":"","battleback2Name":"","bgm":{"name":"","pan":0,"pitch":100,"volume":90},"bgs":{"name":"","pan":0,"pitch":100,"volume":90},"disableDashing":false,"displayName":"Bank","encounterList":[],"encounterStep":30,"height":7,"note":"","parallaxLoopX":false,"parallaxLoopY":false,"parallaxName":"","parallaxShow":true,"parallaxSx":0,"parallaxSy":0,"scrollType":0,"specifyBattleback":false,"tilesetId":3,"width":7,
"data":[7811,7810,7810,7810,7810,7810,7814,7809,7808,7808,7808,7808,7808,7812,7817,7816,7816,7816,7816,7816,7820,1574,1574,1574,1574,1574,1574,1574,1574,1574,1574,1574,1574,1574,1574,1574,1574,1574,1574,1574,1574,1574,1574,1574,1574,1574,1574,1574,1574,0,0,0,0,0,0,0,0,0,0,0,0,0,0,0,0,0,0,0,0,0,0,0,0,0,0,0,0,3569,3569,3569,3569,3569,3569,3569,0,0,0,0,0,0,0,0,0,0,0,0,0,0,0,0,0,0,0,0,0,0,0,0,0,0,0,0,0,0,0,0,0,0,0,0,0,0,0,0,0,0,0,0,0,0,0,0,0,0,0,0,0,0,0,0,0,0,0,0,0,0,0,0,0,0,0,0,160,0,0,173,0,0,0,168,0,0,0,0,0,0,0,0,456,104,0,0,0,104,354,0,0,0,0,0,0,0,0,0,0,0,0,0,0,0,0,0,0,0,0,0,0,0,0,0,0,0,0,0,0,0,0,0,0,0,0,0,0,0,0,0,0,0,0,0,0,0,0,0,0,0,0,0,0,0,0,0,0,0,0,0,0,0,0,0,0,0,0,0,0,0,0,0,0,0,0,0,0,0,0,0,0,0,0,0,0,0,0,0,0,0,0,0,0,0,0,0,0,0,0,0,0,0,0,0,0,0,0,0,0,0,0,0,0,0,0,0,0,0],
"events":[
null,
{"id":1,"name":"BankTeller","note":"","pages":[{"conditions":{"actorId":1,"actorValid":false,"itemId":1,"itemValid":false,"selfSwitchCh":"A","selfSwitchValid":false,"switch1Id":1,"switch1Valid":false,"switch2Id":1,"switch2Valid":false,"variableId":1,"variableValid":false,"variableValue":0},"directionFix":false,"image":{"tileId":0,"characterName":"People1","direction":2,"pattern":1,"characterIndex":4},"list":[{"code":101,"indent":0,"parameters":["People1",4,0,2]},{"code":401,"indent":0,"parameters":["What can I do for you?"]},{"code":102,"indent":0,"parameters":[["Withdraw","Deposit","Nothing"],1,0,2,0]},{"code":402,"indent":0,"parameters":[0,"Withdraw"]},{"code":101,"indent":1,"parameters":["People1",4,0,2]},{"code":401,"indent":1,"parameters":["You have \\V[17] in your account. How much would you like"]},{"code":401,"indent":1,"parameters":["to withdraw?"]},{"code":103,"indent":1,"parameters":[15,6]},{"code":111,"indent":1,"parameters":[1,15,1,17,2]},{"code":122,"indent":2,"parameters":[17,17,2,1,15]},{"code":125,"indent":2,"parameters":[0,1,15]},{"code":101,"indent":2,"parameters":["People1",4,0,2]},{"code":401,"indent":2,"parameters":["Thank you for your business!"]},{"code":0,"indent":2,"parameters":[]},{"code":411,"indent":1,"parameters":[]},{"code":101,"indent":2,"parameters":["People1",4,0,2]},{"code":401,"indent":2,"parameters":["I'm sorry, but you do not have that"]},{"code":401,"indent":2,"parameters":["amount to withdraw."]},{"code":0,"indent":2,"parameters":[]},{"code":412,"indent":1,"parameters":[]},{"code":0,"indent":1,"parameters":[]},{"code":402,"indent":0,"parameters":[1,"Deposit"]},{"code":122,"indent":1,"parameters":[16,16,0,3,7,2,0]},{"code":101,"indent":1,"parameters":["People1",4,0,2]},{"code":401,"indent":1,"parameters":["You have \\V[16] in your wallet. How much would you like"]},{"code":401,"indent":1,"parameters":[" to deposit?"]},{"code":103,"indent":1,"parameters":[15,6]},{"code":111,"indent":1,"parameters":[1,15,1,16,2]},{"code":122,"indent":2,"parameters":[17,17,1,1,15]},{"code":125,"indent":2,"parameters":[1,1,15]},{"code":101,"indent":2,"parameters":["People1",4,0,2]},{"code":401,"indent":2,"parameters":["Thank you for your business!"]},{"code":0,"indent":2,"parameters":[]},{"code":411,"indent":1,"parameters":[]},{"code":101,"indent":2,"parameters":["People1",4,0,2]},{"code":401,"indent":2,"parameters":["I'm sorry, but you do not have that amount to deposit."]},{"code":0,"indent":2,"parameters":[]},{"code":412,"indent":1,"parameters":[]},{"code":0,"indent":1,"parameters":[]},{"code":402,"indent":0,"parameters":[2,"Nothing"]},{"code":101,"indent":1,"parameters":["People1",4,0,2]},{"code":401,"indent":1,"parameters":["Thank you for coming!"]},{"code":0,"indent":1,"parameters":[]},{"code":404,"indent":0,"parameters":[]},{"code":0,"indent":0,"parameters":[]}],"moveFrequency":3,"moveRoute":{"list":[{"code":0,"parameters":[]}],"repeat":true,"skippable":false,"wait":false},"moveSpeed":3,"moveType":0,"priorityType":1,"stepAnime":false,"through":false,"trigger":0,"walkAnime":true}],"x":3,"y":3},
{"id":2,"name":"EV002","note":"","pages":[{"conditions":{"actorId":1,"actorValid":false,"itemId":1,"itemValid":false,"selfSwitchCh":"A","selfSwitchValid":false,"switch1Id":1,"switch1Valid":false,"switch2Id":1,"switch2Valid":false,"variableId":1,"variableValid":false,"variableValue":0},"directionFix":false,"image":{"characterIndex":0,"characterName":"","direction":2,"pattern":0,"tileId":0},"list":[{"code":201,"indent":0,"parameters":[0,16,3,8,0,0]},{"code":250,"indent":0,"parameters":[{"name":"Move1","volume":90,"pitch":100,"pan":0}]},{"code":0,"indent":0,"parameters":[]}],"moveFrequency":3,"moveRoute":{"list":[{"code":0,"parameters":[]}],"repeat":true,"skippable":false,"wait":false},"moveSpeed":3,"moveType":0,"priorityType":0,"stepAnime":false,"through":false,"trigger":0,"walkAnime":true}],"x":3,"y":6}
]
}